borm/__init__.py
borm/database.py
borm/fields.py
borm/manager.py
borm/models.py
borm/settings.py
borm-0.0.1.dist-info/METADATA
borm-0.0.1.dist-info/WHEEL
borm-0.0.1.dist-info/RECORD
