Metadata-Version: 2.1
Name: borm
Version: 0.0.1
Summary: Simple lightweight Django-like ORM for SQLite
License: GPLv3
Author: Baran Erfani
Author-email: erfani.baran@gmail.com
Requires-Python: >=3.6.1,<4.0.0
Classifier: License :: Other/Proprietary License
Classifier: Programming Language :: Python :: 3
Classifier: Programming Language :: Python :: 3.7
Classifier: Programming Language :: Python :: 3.8
Classifier: Programming Language :: Python :: 3.9
Classifier: Programming Language :: Python :: 3.10
Classifier: Programming Language :: Python :: 3.11
Classifier: Programming Language :: Python :: 3.12
